markdown_to_confluence-0.5.4.dist-info/licenses/LICENSE
md2conf/__init__.py
md2conf/__main__.py
md2conf/api.py
md2conf/attachment.py
md2conf/coalesce.py
md2conf/collection.py
md2conf/compatibility.py
md2conf/converter.py
md2conf/csf.py
md2conf/emoticon.py
md2conf/entities.dtd
md2conf/environment.py
md2conf/extension.py
md2conf/external.py
md2conf/formatting.py
md2conf/frontmatter.py
md2conf/image.py
md2conf/latex.py
md2conf/local.py
md2conf/markdown.py
md2conf/matcher.py
md2conf/metadata.py
md2conf/options.py
md2conf/png.py
md2conf/processor.py
md2conf/publisher.py
md2conf/py.typed
md2conf/scanner.py
md2conf/serializer.py
md2conf/svg.py
md2conf/text.py
md2conf/toc.py
md2conf/uri.py
md2conf/xml.py
md2conf/drawio/__init__.py
md2conf/drawio/extension.py
md2conf/drawio/render.py
md2conf/mermaid/__init__.py
md2conf/mermaid/config.py
md2conf/mermaid/extension.py
md2conf/mermaid/puppeteer-config.json
md2conf/mermaid/render.py
md2conf/mermaid/scanner.py
md2conf/plantuml/__init__.py
md2conf/plantuml/config.py
md2conf/plantuml/extension.py
md2conf/plantuml/render.py
md2conf/plantuml/scanner.py
markdown_to_confluence-0.5.4.dist-info/METADATA
markdown_to_confluence-0.5.4.dist-info/WHEEL
markdown_to_confluence-0.5.4.dist-info/entry_points.txt
markdown_to_confluence-0.5.4.dist-info/top_level.txt
markdown_to_confluence-0.5.4.dist-info/zip-safe
markdown_to_confluence-0.5.4.dist-info/RECORD
