Metadata-Version: 2.4
Name: markdown-to-confluence
Version: 0.5.4
Summary: Publish Markdown files to Confluence wiki
Author-email: Levente Hunyadi <hunyadi@gmail.com>
Maintainer-email: Levente Hunyadi <hunyadi@gmail.com>
License-Expression: MIT
Project-URL: Homepage, https://github.com/hunyadi/md2conf
Project-URL: Source, https://github.com/hunyadi/md2conf
Keywords: markdown,converter,confluence
Classifier: Development Status :: 5 - Production/Stable
Classifier: Environment :: Console
Classifier: Intended Audience :: End Users/Desktop
Classifier: Operating System :: OS Independent
Classifier: Programming Language :: Python :: 3
Classifier: Programming Language :: Python :: 3.10
Classifier: Programming Language :: Python :: 3.11
Classifier: Programming Language :: Python :: 3.12
Classifier: Programming Language :: Python :: 3.13
Classifier: Programming Language :: Python :: 3.14
Classifier: Programming Language :: Python :: 3 :: Only
Classifier: Typing :: Typed
Requires-Python: >=3.10
License-File: LICENSE
Requires-Dist: cattrs>=25.3
Requires-Dist: lxml>=6.0
Requires-Dist: markdown>=3.10
Requires-Dist: orjson>=3.11
Requires-Dist: pymdown-extensions>=10.19
Requires-Dist: PyYAML>=6.0
Requires-Dist: requests>=2.32
Requires-Dist: truststore>=0.10
Requires-Dist: typing-extensions>=4.15; python_version < "3.12"
Provides-Extra: dev
Requires-Dist: markdown_doc>=0.1.6; extra == "dev"
Requires-Dist: types-lxml>=2025.11.25; extra == "dev"
Requires-Dist: types-markdown>=3.10; extra == "dev"
Requires-Dist: types-PyYAML>=6.0; extra == "dev"
Requires-Dist: types-requests>=2.32; extra == "dev"
Requires-Dist: mypy>=1.19; extra == "dev"
Requires-Dist: ruff>=0.14; extra == "dev"
Provides-Extra: formulas
Requires-Dist: matplotlib>=3.9; extra == "formulas"
Dynamic: license-file
